streamlit_smart_text_input/__init__.py
streamlit_smart_text_input/example.py
streamlit_smart_text_input/example1.py
streamlit_smart_text_input/frontend/build/asset-manifest.json
streamlit_smart_text_input/frontend/build/bootstrap.min.css
streamlit_smart_text_input/frontend/build/index.html
streamlit_smart_text_input/frontend/build/static/js/main.bd7aa549.js
streamlit_smart_text_input/frontend/build/static/js/main.bd7aa549.js.LICENSE.txt
streamlit_smart_text_input/frontend/build/static/js/main.bd7aa549.js.map
streamlit_smart_text_input/frontend/build/static/media/st-arrow.ed05a8180fdff43803920bbf4086fde9.svg
streamlit_smart_text_input/frontend/build/static/media/st-clear.6e2f7cc05ea4a1c4fe780ea30d5d82a2.svg
streamlit_smart_text_input-1.0.9.dist-info/licenses/LICENCE.md
streamlit_smart_text_input-1.0.9.dist-info/METADATA
streamlit_smart_text_input-1.0.9.dist-info/WHEEL
streamlit_smart_text_input-1.0.9.dist-info/top_level.txt
streamlit_smart_text_input-1.0.9.dist-info/RECORD
