Metadata-Version: 2.4
Name: streamlit-smart-text-input
Version: 1.0.9
Summary: A Streamlit component that allows you to select from a list of options or enter a custom value.
Home-page: 
Author: Ankit Guria
Author-email: ankitguria142@gmail.com
Requires-Python: >=3.9
License-File: LICENCE.md
Requires-Dist: streamlit>=1.25
Provides-Extra: devel
Requires-Dist: wheel; extra == "devel"
Requires-Dist: pytest==7.4.0; extra == "devel"
Requires-Dist: playwright==1.39.0; extra == "devel"
Requires-Dist: requests==2.31.0; extra == "devel"
Requires-Dist: pytest-playwright-snapshot==1.0; extra == "devel"
Requires-Dist: pytest-rerunfailures==12.0; extra == "devel"
Dynamic: author
Dynamic: author-email
Dynamic: description
Dynamic: description-content-type
Dynamic: license-file
Dynamic: provides-extra
Dynamic: requires-dist
Dynamic: requires-python
Dynamic: summary
